Metadata-Version: 2.2
Name: cli2
Version: 5.2.3
Summary: image:: https://yourlabs.io/oss/cli2/badges/master/pipeline.svg
Home-page: https://yourlabs.io/oss/cli2
Author: James Pic
Author-email: jamespic@gmail.com
License: MIT
Keywords: cli
Requires-Python: >=3.6
Requires-Dist: docstring_parser
Requires-Dist: pyyaml
Requires-Dist: pygments
Requires-Dist: structlog
Provides-Extra: httpx
Requires-Dist: chttpx; extra == "httpx"
Provides-Extra: ansible
Requires-Dist: cansible; extra == "ansible"
Provides-Extra: test
Requires-Dist: freezegun; extra == "test"
Requires-Dist: pytest; extra == "test"
Requires-Dist: pytest-cov; extra == "test"
Requires-Dist: pytest-mock; extra == "test"
Requires-Dist: pytest-asyncio; extra == "test"
Requires-Dist: pytest-httpx; extra == "test"
Dynamic: author
Dynamic: author-email
Dynamic: description
Dynamic: description-content-type
Dynamic: home-page
Dynamic: keywords
Dynamic: license
Dynamic: provides-extra
Dynamic: requires-dist
Dynamic: requires-python
Dynamic: summary
